infra/__init__.py
infra/conftest.py
infra/setup.py
infra/drivers/__init__.py
infra/drivers/browser_base.py
infra/drivers/mysql_conn.py
infra/drivers/performance.py
infra/drivers/settings.py
infra/helpers/__init__.py
infra/helpers/afw_decorators.py
infra/helpers/login_ui.py
infra/helpers/playwright_helpers.py
infra/helpers/tools.py
infra/template/__init__.py
infra/template/conftest.py
infra/template/navigation_tests.py
afw-0.0.21.dist-info/LICENSE
afw-0.0.21.dist-info/METADATA
afw-0.0.21.dist-info/WHEEL
afw-0.0.21.dist-info/top_level.txt
afw-0.0.21.dist-info/RECORD
