Metadata-Version: 2.1
Name: afw
Version: 0.0.21
Summary: -
Home-page: https://github.com/tsachikotek/AFW
Author: Tsachi Kotek
Author-email: tsachikotek@gmail.com
License-File: LICENSE
Requires-Dist: allure-python-commons==2.13.5
Requires-Dist: attrs==24.2.0
Requires-Dist: certifi==2024.8.30
Requires-Dist: charset-normalizer==3.3.2
Requires-Dist: docutils==0.21.2
Requires-Dist: greenlet==3.0.3
Requires-Dist: idna==3.10
Requires-Dist: importlib-metadata==8.5.0
Requires-Dist: iniconfig==2.0.0
Requires-Dist: jaraco.classes==3.4.0
Requires-Dist: jaraco.context==6.0.1
Requires-Dist: jaraco.functools==4.1.0
Requires-Dist: keyring==25.4.1
Requires-Dist: markdown-it-py==3.0.0
Requires-Dist: mdurl==0.1.2
Requires-Dist: more-itertools==10.5.0
Requires-Dist: mysql-connector-python==9.0.0
Requires-Dist: nest-asyncio==1.6.0
Requires-Dist: nh3==0.2.18
Requires-Dist: packaging==24.1
Requires-Dist: pkginfo==1.10.0
Requires-Dist: playwright==1.46.0
Requires-Dist: pluggy==1.5.0
Requires-Dist: pyee==11.1.0
Requires-Dist: Pygments==2.18.0
Requires-Dist: pytest-asyncio==0.24.0
Requires-Dist: pytest-base-url==2.1.0
Requires-Dist: pytest-ordering==0.6
Requires-Dist: pytest-playwright==0.5.2
Requires-Dist: pytest==8.3.2
Requires-Dist: python-slugify==8.0.4
Requires-Dist: readme-renderer==44.0
Requires-Dist: requests-toolbelt==1.0.0
Requires-Dist: requests==2.32.3
Requires-Dist: rfc3986==2.0.0
Requires-Dist: rich==13.8.1
Requires-Dist: setuptools==75.1.0
Requires-Dist: text-unidecode==1.3
Requires-Dist: twine==5.1.1
Requires-Dist: typing-extensions==4.12.2
Requires-Dist: urllib3==2.2.3
Requires-Dist: wheel==0.44.0
Requires-Dist: zipp==3.20.2
